rolepermissions/__init__.py
rolepermissions/admin.py
rolepermissions/apps.py
rolepermissions/checkers.py
rolepermissions/decorators.py
rolepermissions/exceptions.py
rolepermissions/loader.py
rolepermissions/mixins.py
rolepermissions/models.py
rolepermissions/permissions.py
rolepermissions/roles.py
rolepermissions/utils.py
rolepermissions/management/__init__.py
rolepermissions/management/commands/__init__.py
rolepermissions/management/commands/sync_roles.py
rolepermissions/templatetags/__init__.py
rolepermissions/templatetags/permission_tags.py
django_role_permissions-3.2.0.dist-info/LICENSE
django_role_permissions-3.2.0.dist-info/METADATA
django_role_permissions-3.2.0.dist-info/WHEEL
django_role_permissions-3.2.0.dist-info/top_level.txt
django_role_permissions-3.2.0.dist-info/RECORD
